swrf/__init__.py
swrf/check.py
swrf/config.py
swrf/database.py
swrf/publish/__init__.py
swrf/publish/check.py
swrf/subscribe/__init__.py
swrf/subscribe/database_check.py
swrf/subscribe/print_check.py
swrf-0.1.3.dist-info/METADATA
swrf-0.1.3.dist-info/WHEEL
swrf-0.1.3.dist-info/licenses/LICENSE.md
swrf-0.1.3.dist-info/RECORD
