Metadata-Version: 2.1
Name: swrf
Version: 0.1.3
Summary: swrf / sorrowful - Check internet connection
Project-URL: Homepage, https://github.com/ceesvandegriend/swrf
Project-URL: Source, https://github.com/ceesvandegriend/swrf
Author-email: Cees van de Griend <cees@griend.eu>
Maintainer-email: Cees van de Griend <cees@griend.eu>
License: ### GNU GENERAL PUBLIC LICENSE
License-File: LICENSE.md
Keywords: apachemq,check
Classifier: Development Status :: 3 - Alpha
Classifier: License :: OSI Approved :: GNU General Public License v3 or later (GPLv3+)
Classifier: Programming Language :: Python :: 3 :: Only
Classifier: Programming Language :: Python :: 3.9
Classifier: Programming Language :: Python :: 3.10
Classifier: Programming Language :: Python :: 3.11
Requires-Python: >=3.9
Requires-Dist: requests
Requires-Dist: stomp-py
